[{"ticker": "JPM", "currentPrice": 116.11, "dividend": "3.60 (3.07%)", "exDividendDate": "Oct 05, 2020", "PERatio": "15.14", "EPS": "7.67", "sharesOwned": 1.1813487, "valueOfHolding": 137.17, "valueOfHoldingInEuro": "115.61"}, {"ticker": "T", "currentPrice": 29.03, "dividend": "2.08 (7.18%)", "exDividendDate": "Oct 08, 2020", "PERatio": "19.10", "EPS": "1.52", "sharesOwned": 8.513788, "valueOfHolding": 247.16, "valueOfHoldingInEuro": "208.31"}, {"ticker": "ABBV", "currentPrice": 99.21, "dividend": "5.20 (5.29%)", "exDividendDate": "Jan 14, 2021", "PERatio": "21.70", "EPS": "4.57", "sharesOwned": 1.769657, "valueOfHolding": 175.57, "valueOfHoldingInEuro": "147.97"}, {"ticker": "MMM", "currentPrice": 173.64, "dividend": "5.88 (3.38%)", "exDividendDate": "Nov 19, 2020", "PERatio": "20.36", "EPS": "8.53", "sharesOwned": 1, "valueOfHolding": 173.64, "valueOfHoldingInEuro": "146.35"}, {"ticker": "BMO", "currentPrice": 69.4, "dividend": "3.21 (4.67%)", "exDividendDate": "Oct 30, 2020", "PERatio": "11.30", "EPS": "6.14", "sharesOwned": 3, "valueOfHolding": 208.2, "valueOfHoldingInEuro": "175.47"}, {"ticker": "KO", "currentPrice": 53.68, "dividend": "1.64 (3.05%)", "exDividendDate": "Nov 30, 2020", "PERatio": "27.81", "EPS": "1.93", "sharesOwned": 3, "valueOfHolding": 161.04, "valueOfHoldingInEuro": "135.73"}, {"ticker": "BNS", "currentPrice": 47.36, "dividend": "2.73 (5.76%)", "exDividendDate": "Oct 05, 2020", "PERatio": "9.24", "EPS": "5.12", "sharesOwned": 3.69765, "valueOfHolding": 175.12, "valueOfHoldingInEuro": "147.59"}, {"ticker": "CL", "currentPrice": 85.35, "dividend": "1.76 (2.05%)", "exDividendDate": "Oct 22, 2020", "PERatio": "27.27", "EPS": "3.13", "sharesOwned": 2, "valueOfHolding": 170.7, "valueOfHoldingInEuro": "143.87"}, {"ticker": "CSCO", "currentPrice": 41.88, "dividend": "1.44 (3.39%)", "exDividendDate": "Oct 01, 2020", "PERatio": "16.96", "EPS": "2.47", "sharesOwned": 0, "valueOfHolding": 0.0, "valueOfHoldingInEuro": "0.00"}, {"ticker": "JNJ", "currentPrice": 149.35, "dividend": "4.04 (2.68%)", "exDividendDate": "Nov 23, 2020", "PERatio": "23.48", "EPS": "6.36", "sharesOwned": 1.336297, "valueOfHolding": 199.58, "valueOfHoldingInEuro": "168.21"}, {"ticker": "LEG", "currentPrice": 42.76, "dividend": "1.60 (3.73%)", "exDividendDate": "Dec 14, 2020", "PERatio": "25.15", "EPS": "1.70", "sharesOwned": 3.841383, "valueOfHolding": 164.26, "valueOfHoldingInEuro": "138.44"}, {"ticker": "MRK", "currentPrice": 81.5, "dividend": "2.44 (3.04%)", "exDividendDate": "Sep 14, 2020", "PERatio": "18.00", "EPS": "4.53", "sharesOwned": 1.566231, "valueOfHolding": 127.65, "valueOfHoldingInEuro": "107.59"}, {"ticker": "PEP", "currentPrice": 145.24, "dividend": "4.09 (2.81%)", "exDividendDate": "Sep 03, 2020", "PERatio": "28.76", "EPS": "5.05", "sharesOwned": 1, "valueOfHolding": 145.24, "valueOfHoldingInEuro": "122.41"}, {"ticker": "O", "currentPrice": 62.82, "dividend": "2.81 (4.36%)", "exDividendDate": "Nov 30, 2020", "PERatio": "52.31", "EPS": "1.20", "sharesOwned": 3, "valueOfHolding": 188.46, "valueOfHoldingInEuro": "158.84"}, {"ticker": "STOR", "currentPrice": 32.23, "dividend": "1.44 (4.42%)", "exDividendDate": "Sep 29, 2020", "PERatio": "36.58", "EPS": "0.88", "sharesOwned": 5.214147, "valueOfHolding": 168.05, "valueOfHoldingInEuro": "141.64"}, {"ticker": "VZ", "currentPrice": 60.75, "dividend": "2.51 (4.12%)", "exDividendDate": "Oct 08, 2020", "PERatio": "13.74", "EPS": "4.42", "sharesOwned": 2.694595, "valueOfHolding": 163.7, "valueOfHoldingInEuro": "137.97"}]